loracrypto/__init__.py
loradefs/__init__.py
loramsg/__init__.py
loraopts/__init__.py
rtlib/__init__.py
rtlib/eui.py
rtlib/types.py
liblora-0.0.3.dist-info/LICENSE
liblora-0.0.3.dist-info/METADATA
liblora-0.0.3.dist-info/WHEEL
liblora-0.0.3.dist-info/top_level.txt
liblora-0.0.3.dist-info/RECORD
